protoplast/__init__.py
protoplast/__main__.py
protoplast/utils.py
protoplast/genomics/__init__.py
protoplast/genomics/vcf/__init__.py
protoplast/genomics/vcf/_vcf.py
protoplast/genomics/vcf/scan.py
protoplast/patches/README.md
protoplast/patches/__init__.py
protoplast/patches/anndata_read_h5ad_backed.py
protoplast/patches/anndata_remote.py
protoplast/patches/daft_flotilla.py
protoplast/patches/file_handler.py
protoplast/scrna/__init__.py
protoplast/scrna/anndata/__init__.py
protoplast/scrna/anndata/_anndata.py
protoplast/scrna/anndata/lightning_models.py
protoplast/scrna/anndata/scan.py
protoplast/scrna/anndata/strategy.py
protoplast/scrna/anndata/torch_dataloader.py
protoplast/scrna/anndata/trainer.py
protoplast-0.1.3.dist-info/METADATA
protoplast-0.1.3.dist-info/WHEEL
protoplast-0.1.3.dist-info/licenses/LICENSE
protoplast-0.1.3.dist-info/RECORD
